Metadata-Version: 1.1
Name: sarltdtgore
Version: 0.1
Summary: A random test lib
Home-page: https://github.com/radolfterminator/
Author: Peter Downs
Author-email: peterldowns@gmail.com
License: UNKNOWN
Download-URL: https://github.com/radolfterminator/ae/blob/master/1.tar.gz
Keywords: testing,logging,example
Platform: UNKNOWN
